wisestork/__init__.py
wisestork/count.py
wisestork/gc.py
wisestork/gc_correct.py
wisestork/newref.py
wisestork/utils.py
wisestork/wisestork.py
wisestork/ztest.py
wisestork-0.1.2.dist-info/AUTHORS
wisestork-0.1.2.dist-info/LICENSE
wisestork-0.1.2.dist-info/METADATA
wisestork-0.1.2.dist-info/WHEEL
wisestork-0.1.2.dist-info/entry_points.txt
wisestork-0.1.2.dist-info/top_level.txt
wisestork-0.1.2.dist-info/RECORD
