Metadata-Version: 2.1
Name: wisestork
Version: 0.1.2
Summary: Within-sample CNV calling
Home-page: https://github.com/sndrtj/wisestork
Author: Sander Bollen
Author-email: sander@sndrtj.eu
License: GPLv3+
Platform: UNKNOWN
Classifier: License :: OSI Approved :: GNU General Public License v3 or later (GPLv3+)
Classifier: Topic :: Scientific/Engineering :: Bio-Informatics
Classifier: Programming Language :: Python :: 3 :: Only
Classifier: Programming Language :: Python :: 3.5
Classifier: Programming Language :: Python :: 3.6
Classifier: Programming Language :: Python :: 3.7
Requires-Python: >=3.5
Requires-Dist: numpy
Requires-Dist: matplotlib
Requires-Dist: statsmodels
Requires-Dist: pysam
Requires-Dist: pyfaidx
Requires-Dist: biopython
Requires-Dist: scipy
Requires-Dist: click
Requires-Dist: progressbar2
